talerbank/__init__.py
talerbank/app/__init__.py
talerbank/app/admin.py
talerbank/app/locale/de/LC_MESSAGES/django.mo
talerbank/app/locale/django.pot
talerbank/app/locale/es/LC_MESSAGES/django.mo
talerbank/app/locale/fr/LC_MESSAGES/django.mo
talerbank/app/locale/it/LC_MESSAGES/django.mo
talerbank/app/locale/ja/LC_MESSAGES/django.mo
talerbank/app/locale/pt/LC_MESSAGES/django.mo
talerbank/app/locale/ru/LC_MESSAGES/django.mo
talerbank/app/locale/sv/LC_MESSAGES/django.mo
talerbank/app/management/__init__.py
talerbank/app/management/commands/__init__.py
talerbank/app/management/commands/add_bank_account.py
talerbank/app/management/commands/changepassword_unsafe.py
talerbank/app/management/commands/list_accounts.py
talerbank/app/management/commands/provide_accounts.py
talerbank/app/management/commands/top_up.py
talerbank/app/management/commands/wire_transfer.py
talerbank/app/management/commands/wire_transfer_payto.py
talerbank/app/middleware.py
talerbank/app/migrations/0001_initial.py
talerbank/app/migrations/__init__.py
talerbank/app/models.py
talerbank/app/schemas.py
talerbank/app/static/bank.css
talerbank/app/static/demo.css
talerbank/app/static/disabled-button.css
talerbank/app/static/favicon.ico
talerbank/app/static/logo-white.svg
talerbank/app/static/profile-page.js
talerbank/app/static/pure.css
talerbank/app/templates/404.html
talerbank/app/templates/base.html
talerbank/app/templates/common_base.html
talerbank/app/templates/login.html
talerbank/app/templates/payto_wiretransfer.html
talerbank/app/templates/profile_page.html
talerbank/app/templates/public_accounts.html
talerbank/app/templates/register.html
talerbank/app/templates/wiretransfer.html
talerbank/app/templates/withdraw_confirm.html
talerbank/app/templates/withdraw_show.html
talerbank/app/testconfigs/bank-check-alt-badamount.conf
talerbank/app/testconfigs/bank-check-alt-nocurrency.conf
talerbank/app/testconfigs/bank-check.conf
talerbank/app/tests.py
talerbank/app/urls.py
talerbank/app/views.py
talerbank-0.8.2.dist-info/entry_points.txt
talerbank-0.8.2.dist-info/COPYING
talerbank-0.8.2.dist-info/WHEEL
talerbank-0.8.2.dist-info/METADATA
talerbank-0.8.2.dist-info/RECORD
