Metadata-Version: 2.1
Name: talerbank
Version: 0.8.2
Summary: Taler demo bank
License: GPL-3.0-or-later
Author: Marcello Stanisci
Author-email: ms@taler.net
Requires-Python: >=3.8,<4.0
Classifier: License :: OSI Approved :: GNU General Public License v3 or later (GPLv3+)
Classifier: Programming Language :: Python :: 3
Classifier: Programming Language :: Python :: 3.8
Classifier: Programming Language :: Python :: 3.9
Requires-Dist: Babel (>=2.8.0,<3.0.0)
Requires-Dist: Jinja2 (>=3.0.0,<4.0.0)
Requires-Dist: click (>=7.1.2,<8.0.0)
Requires-Dist: django (>=3.1.3,<4.0.0)
Requires-Dist: lxml (>=4.6.1,<5.0.0)
Requires-Dist: psycopg2 (>=2.8.6,<3.0.0)
Requires-Dist: qrcode (>=6.1,<7.0)
Requires-Dist: requests (>=2.24.0,<3.0.0)
Requires-Dist: taler-util (>=0.8.3,<0.9.0)
Requires-Dist: uWSGI (>=2.0.19,<3.0.0)
